{
  "documents": [
    {
      "keyPhrases": [
        "punta filosa", 
        "equipaje de mano", 
        "paraguas"
      ], 
      "id": "10155157453696033_10155159503026033"
    }, 
    {
      "keyPhrases": [
        "desayuno", 
        "alicante", 
        "hotel", 
        "miercoles", 
        "an portado", 
        "vuelo de paris"
      ], 
      "id": "10155157453696033_10155159741156033"
    }, 
    {
      "keyPhrases": [
        "Alex Zurita"
      ], 
      "id": "10155157453696033_10155159756986033"
    }, 
    {
      "keyPhrases": [
        "dias de vacaciones", 
        "habeis resondido", 
        "habeis hecho", 
        "dias de crucero", 
        "lis habeis roto", 
        "gastos de transporte", 
        "Xunta", 
        "alojamiento", 
        "comidas", 
        "sueños", 
        "Estais de coña", 
        "publicidad", 
        "despues", 
        "negligencia", 
        "contestacion indemnización", 
        "parte", 
        "Napoles", 
        "ofreceis", 
        "temgo", 
        "avion"
      ], 
      "id": "10155157453696033_10155159763466033"
    }, 
    {
      "keyPhrases": [
        "Lisboa a Barcelona latas pequeñas", 
        "conserva", 
        "equipajo de mano", 
        "sardinas", 
        "Buenas tardes"
      ], 
      "id": "10155157453696033_10155159850366033"
    }, 
    {
      "keyPhrases": [
        "pregunta", 
        "repito"
      ], 
      "id": "10155157453696033_10155160441261033"
    }, 
    {
      "keyPhrases": [
        "Gemma Mh Eldiana Iomotin", 
        "Jolin"
      ], 
      "id": "10155157453696033_10155160822056033"
    }, 
    {
      "keyPhrases": [
        "fantástica Compañía Vueling"
      ], 
      "id": "10155157453696033_10155163276776033"
    }, 
    {
      "keyPhrases": [
        "frecuencias", 
        "Gran Canaria a  París", 
        "saludo"
      ], 
      "id": "10155157453696033_10155165849256033"
    }, 
    {
      "keyPhrases": [
        "carrito Peg Perego Booklet", 
        "costo adicional", 
        "bebe"
      ], 
      "id": "10155157453696033_10155165897281033"
    }, 
    {
      "keyPhrases": [
        "primo"
      ], 
      "id": "10155158389271033_10155160516066033"
    }, 
    {
      "keyPhrases": [
        "Jajjajaja"
      ], 
      "id": "10155158389271033_10155160522811033"
    }, 
    {
      "keyPhrases": [
        "público jajajajaja"
      ], 
      "id": "10155158389271033_10155160525806033"
    }, 
    {
      "keyPhrases": [
        "Yaaaá"
      ], 
      "id": "10155158389271033_10155160526451033"
    }, 
    {
      "keyPhrases": [
        "customer experience pèssima"
      ], 
      "id": "10155158069616033_10155158120021033"
    }, 
    {
      "keyPhrases": [
        "ningun tipo de explicacion", 
        "reserva", 
        "condiciones de compra", 
        "llamadas", 
        "aeropuerto"
      ], 
      "id": "10155157617031033_10155157639721033"
    }, 
    {
      "keyPhrases": [
        "Referencia NBCQ3G", 
        "venecia a barcelona"
      ], 
      "id": "10155157617031033_10155157664141033"
    }, 
    {
      "keyPhrases": [
        "gracias", 
        "Hola", 
        "pronta respuesta"
      ], 
      "id": "10155157598926033_10155157663261033"
    }, 
    {
      "keyPhrases": [
        "disculpas x", 
        "siguiente dia", 
        "Ibiza x desperfectos mecanicos", 
        "siguiente vino completo", 
        "vuelo Barce", 
        "hs", 
        "madrugada", 
        "atraso", 
        "fin", 
        "destino", 
        "Vueling"
      ], 
      "id": "10155157404731033_10155158139866033"
    }, 
    {
      "keyPhrases": [
        "Muxas gracias", 
        "departamento", 
        "problema", 
        "Agradeceria q"
      ], 
      "id": "10155157128586033_10155157142641033"
    }, 
    {
      "keyPhrases": [
        "gracias", 
        "plazo"
      ], 
      "id": "10155156805181033_10155156896831033"
    }, 
    {
      "keyPhrases": [
        "maridin"
      ], 
      "id": "10155156742626033_10155156745021033"
    }, 
    {
      "keyPhrases": [
        "Francisco Gonzalez vamonos a Italiaaaaaaa"
      ], 
      "id": "10155156742626033_10155156745951033"
    }, 
    {
      "keyPhrases": [
        "musulmana", 
        "Rubina Hermelo"
      ], 
      "id": "10155156742626033_10155156745996033"
    }, 
    {
      "keyPhrases": [
        "Manuela Navas Nieto"
      ], 
      "id": "10155156742626033_10155156746016033"
    }, 
    {
      "keyPhrases": [
        "Venecia", 
        "Neus Quintero"
      ], 
      "id": "10155156742626033_10155156746996033"
    }, 
    {
      "keyPhrases": [
        "José Manuel León Fernández", 
        "piaceeeeee 😍😍😍 Andiamo"
      ], 
      "id": "10155156742626033_10155156747256033"
    }, 
    {
      "keyPhrases": [
        "Dave Guillén"
      ], 
      "id": "10155156742626033_10155156747436033"
    }, 
    {
      "keyPhrases": [
        "Sandra Menendez Garcia"
      ], 
      "id": "10155156742626033_10155156747671033"
    }, 
    {
      "keyPhrases": [
        "amigui"
      ], 
      "id": "10155156742626033_10155156747726033"
    }, 
    {
      "keyPhrases": [
        "Andres Seco García"
      ], 
      "id": "10155156742626033_10155156748001033"
    }, 
    {
      "keyPhrases": [
        "Alex Lorenzo", 
        "Italia"
      ], 
      "id": "10155156742626033_10155156748051033"
    }, 
    {
      "keyPhrases": [
        "enlace xa", 
        "página"
      ], 
      "id": "10155156742626033_10155156748081033"
    }, 
    {
      "keyPhrases": [
        "yas"
      ], 
      "id": "10155156742626033_10155156748326033"
    }, 
    {
      "keyPhrases": [
        "Jorge J Barrio"
      ], 
      "id": "10155156742626033_10155156748931033"
    }, 
    {
      "keyPhrases": [
        "Belen Baamonde Gomez"
      ], 
      "id": "10155156742626033_10155156749086033"
    }, 
    {
      "keyPhrases": [
        "Oscar Fernández Rodríguez a Venecia"
      ], 
      "id": "10155156742626033_10155156749141033"
    }, 
    {
      "keyPhrases": [
        "Gema Gemita"
      ], 
      "id": "10155156742626033_10155156749521033"
    }, 
    {
      "keyPhrases": [
        "Alvaro Jimenez", 
        "vespa", 
        "Roma"
      ], 
      "id": "10155156742626033_10155156749606033"
    }, 
    {
      "keyPhrases": [
        "Vueling"
      ], 
      "id": "10155156742626033_10155156749656033"
    }, 
    {
      "keyPhrases": [
        "Carlos Setién Fontecilla"
      ], 
      "id": "10155156742626033_10155156749726033"
    }, 
    {
      "keyPhrases": [
        "José Antonio Rodríguez Ortega"
      ], 
      "id": "10155156742626033_10155156750021033"
    }, 
    {
      "keyPhrases": [
        "Karina Romero"
      ], 
      "id": "10155156742626033_10155156750066033"
    }, 
    {
      "keyPhrases": [
        "Iva Angelova vamonos"
      ], 
      "id": "10155156742626033_10155156750086033"
    }, 
    {
      "keyPhrases": [
        "mejor compañia de Jéssica Alfranca", 
        "buen viaje"
      ], 
      "id": "10155156742626033_10155156750131033"
    }, 
    {
      "keyPhrases": [
        "Fina Rejillas"
      ], 
      "id": "10155156742626033_10155156750156033"
    }, 
    {
      "keyPhrases": [
        "Cristina Llopart Gómez asi", 
        "rl idioma jejejjejeje"
      ], 
      "id": "10155156742626033_10155156750271033"
    }, 
    {
      "keyPhrases": [
        "Rocio Madueño"
      ], 
      "id": "10155156742626033_10155156750311033"
    }, 
    {
      "keyPhrases": [
        "Ana Isabel Martínez Antón"
      ], 
      "id": "10155156742626033_10155156750321033"
    }, 
    {
      "keyPhrases": [
        "chico Javier Muñoz ojal", 
        "suerte gracias vueling", 
        "Venecia"
      ], 
      "id": "10155156742626033_10155156750361033"
    }, 
    {
      "keyPhrases": [
        "Maria Rosa Losada"
      ], 
      "id": "10155156742626033_10155156750471033"
    }, 
    {
      "keyPhrases": [
        "José Lluesma", 
        "día"
      ], 
      "id": "10155156742626033_10155156750476033"
    }, 
    {
      "keyPhrases": [
        "Imanol Leja Raga"
      ], 
      "id": "10155156742626033_10155156750621033"
    }, 
    {
      "keyPhrases": [
        "Iria"
      ], 
      "id": "10155156742626033_10155156750636033"
    }, 
    {
      "keyPhrases": [], 
      "id": "10155156742626033_10155156750726033"
    }, 
    {
      "keyPhrases": [
        "Fermin Txo", 
        "Venecia"
      ], 
      "id": "10155156742626033_10155156750846033"
    }, 
    {
      "keyPhrases": [
        "Benito Mateo"
      ], 
      "id": "10155156742626033_10155156750876033"
    }, 
    {
      "keyPhrases": [
        "Raquel Raigón Ruz", 
        "fotos", 
        "acompañaríassss"
      ], 
      "id": "10155156742626033_10155156750931033"
    }, 
    {
      "keyPhrases": [
        "Bruno Robbio"
      ], 
      "id": "10155156742626033_10155156750946033"
    }, 
    {
      "keyPhrases": [
        "Pablo Alberto Veira Alvarez", 
        "viajecito a Italia"
      ], 
      "id": "10155156742626033_10155156751021033"
    }, 
    {
      "keyPhrases": [
        "Martín"
      ], 
      "id": "10155156742626033_10155156751121033"
    }, 
    {
      "keyPhrases": [
        "Ana Carrion italia"
      ], 
      "id": "10155156742626033_10155156751256033"
    }, 
    {
      "keyPhrases": [
        "Lena Orts Drago"
      ], 
      "id": "10155156742626033_10155156751266033"
    }, 
    {
      "keyPhrases": [
        "página", 
        "promo"
      ], 
      "id": "10155156742626033_10155156751331033"
    }, 
    {
      "keyPhrases": [
        "Marga Benejam Enrich"
      ], 
      "id": "10155156742626033_10155156751336033"
    }, 
    {
      "keyPhrases": [
        "Céline Ripert"
      ], 
      "id": "10155156742626033_10155156751436033"
    }, 
    {
      "keyPhrases": [
        "Carlos Moral"
      ], 
      "id": "10155156742626033_10155156751521033"
    }, 
    {
      "keyPhrases": [
        "Gema Gamarra a Venecia", 
        "suerte Vueling"
      ], 
      "id": "10155156742626033_10155156751656033"
    }, 
    {
      "keyPhrases": [
        "hermana Anita Alejandra Fernandez pasta per tutti", 
        "iria", 
        "totalidad", 
        "gif", 
        "comida", 
        "Italia", 
        "gracias", 
        "suerte"
      ], 
      "id": "10155156742626033_10155156751696033"
    }, 
    {
      "keyPhrases": [
        "Gar Pa"
      ], 
      "id": "10155156742626033_10155156751721033"
    }, 
    {
      "keyPhrases": [
        "Susana GC"
      ], 
      "id": "10155156742626033_10155156751841033"
    }, 
    {
      "keyPhrases": [
        "hermana Mar Trillo Sánchez", 
        "Roma"
      ], 
      "id": "10155156742626033_10155156751846033"
    }, 
    {
      "keyPhrases": [
        "Peloz", 
        "aver"
      ], 
      "id": "10155156742626033_10155156751851033"
    }, 
    {
      "keyPhrases": [
        "Erica Sánchez López"
      ], 
      "id": "10155156742626033_10155156753051033"
    }, 
    {
      "keyPhrases": [
        "maridito"
      ], 
      "id": "10155156742626033_10155156753121033"
    }, 
    {
      "keyPhrases": [
        "Rosa Mari Mateos"
      ], 
      "id": "10155156742626033_10155156753166033"
    }, 
    {
      "keyPhrases": [
        "Italia"
      ], 
      "id": "10155156742626033_10155156753206033"
    }, 
    {
      "keyPhrases": [
        "Natalia Accomazzo Scotti"
      ], 
      "id": "10155156742626033_10155156754076033"
    }, 
    {
      "keyPhrases": [
        "Almu Delgado"
      ], 
      "id": "10155156742626033_10155156754296033"
    }, 
    {
      "keyPhrases": [
        "super sister", 
        "Belen Garcia Hernansanz", 
        "suerteeeee"
      ], 
      "id": "10155156742626033_10155156754721033"
    }, 
    {
      "keyPhrases": [
        "Josep Barrios Rojo"
      ], 
      "id": "10155156742626033_10155156754756033"
    }, 
    {
      "keyPhrases": [
        "Susana Bolaños"
      ], 
      "id": "10155156742626033_10155156754836033"
    }, 
    {
      "keyPhrases": [
        "edujibe"
      ], 
      "id": "10155156742626033_10155156755216033"
    }, 
    {
      "keyPhrases": [
        "Carmen Moral Moral"
      ], 
      "id": "10155156742626033_10155156755271033"
    }, 
    {
      "keyPhrases": [
        "Palermo"
      ], 
      "id": "10155156742626033_10155156755381033"
    }, 
    {
      "keyPhrases": [
        "Alicia Muñiz Lana"
      ], 
      "id": "10155156742626033_10155156755386033"
    }, 
    {
      "keyPhrases": [
        "Eduard Jimenez"
      ], 
      "id": "10155156742626033_10155156755411033"
    }, 
    {
      "keyPhrases": [
        "Maribel Campo Morro"
      ], 
      "id": "10155156742626033_10155156755521033"
    }, 
    {
      "keyPhrases": [
        "Jorge Garri amoreee", 
        "Italia"
      ], 
      "id": "10155156742626033_10155156755581033"
    }, 
    {
      "keyPhrases": [
        "ganas", 
        "Florencia", 
        "Itziar Esteban", 
        "sitio"
      ], 
      "id": "10155156742626033_10155156755661033"
    }, 
    {
      "keyPhrases": [
        "Raul Eduardo Rion"
      ], 
      "id": "10155156742626033_10155156755726033"
    }, 
    {
      "keyPhrases": [
        "mundo bueno", 
        "fin", 
        "Jose Manuel Lopez", 
        "ocasión"
      ], 
      "id": "10155156742626033_10155156755921033"
    }, 
    {
      "keyPhrases": [
        "Virginia", 
        "facebook", 
        "inconveniente"
      ], 
      "id": "10155156742626033_10155156755956033"
    }, 
    {
      "keyPhrases": [
        "Ramiro Ruiz suerte"
      ], 
      "id": "10155156742626033_10155156756521033"
    }, 
    {
      "keyPhrases": [
        "Carlos Prados Gómez"
      ], 
      "id": "10155156742626033_10155156756676033"
    }, 
    {
      "keyPhrases": [
        "Nacho Matia"
      ], 
      "id": "10155156742626033_10155156756681033"
    }, 
    {
      "keyPhrases": [
        "Josep Barrios Rojo"
      ], 
      "id": "10155156742626033_10155156756691033"
    }, 
    {
      "keyPhrases": [
        "Soso Mcebo"
      ], 
      "id": "10155156742626033_10155156756766033"
    }, 
    {
      "keyPhrases": [
        "suerte"
      ], 
      "id": "10155156742626033_10155156756831033"
    }, 
    {
      "keyPhrases": [
        "Roma", 
        "Ana Andrade"
      ], 
      "id": "10155156742626033_10155156756856033"
    }, 
    {
      "keyPhrases": [
        "Victor SG"
      ], 
      "id": "10155156742626033_10155156757041033"
    }, 
    {
      "keyPhrases": [
        "hija"
      ], 
      "id": "10155156742626033_10155156757096033"
    }, 
    {
      "keyPhrases": [
        "Diana Argelich Isern"
      ], 
      "id": "10155156742626033_10155156757216033"
    }, 
    {
      "keyPhrases": [
        "Roma", 
        "verdad Oliver Bufill Gobern", 
        "billetes", 
        "excusa"
      ], 
      "id": "10155156742626033_10155156757401033"
    }, 
    {
      "keyPhrases": [
        "Helena Garvín López"
      ], 
      "id": "10155156742626033_10155156757461033"
    }, 
    {
      "keyPhrases": [
        "Adrián Álvarez Muñoz", 
        "Roma", 
        "sitio"
      ], 
      "id": "10155156742626033_10155156757731033"
    }, 
    {
      "keyPhrases": [
        "Noelia Lorenzo Díaz"
      ], 
      "id": "10155156742626033_10155156757781033"
    }, 
    {
      "keyPhrases": [
        "iria", 
        "Charles Gregori Toja Muiños"
      ], 
      "id": "10155156742626033_10155156757796033"
    }, 
    {
      "keyPhrases": [
        "Rebecca Charles"
      ], 
      "id": "10155156742626033_10155156757961033"
    }, 
    {
      "keyPhrases": [
        "Reyes Santos Maclanda"
      ], 
      "id": "10155156742626033_10155156757966033"
    }, 
    {
      "keyPhrases": [
        "Venecia", 
        "Francisco Crespo Diaz"
      ], 
      "id": "10155156742626033_10155156758021033"
    }, 
    {
      "keyPhrases": [
        "Carlos Alberto Huskisson Jones", 
        "ilusión"
      ], 
      "id": "10155156742626033_10155156758076033"
    }, 
    {
      "keyPhrases": [
        "Juan Pacheco", 
        "bella Italia"
      ], 
      "id": "10155156742626033_10155156758131033"
    }, 
    {
      "keyPhrases": [
        "Verona", 
        "Florencia", 
        "Lucca", 
        "Edgar Erena Chacón Roma", 
        "Lago", 
        "Garda", 
        "bella italia", 
        "VuelingLlevádnosAlaBonitaVenecia"
      ], 
      "id": "10155156742626033_10155156758141033"
    }, 
    {
      "keyPhrases": [
        "Elizabeth", 
        "escapadita a Milán", 
        "Roma"
      ], 
      "id": "10155156742626033_10155156758206033"
    }, 
    {
      "keyPhrases": [
        "Pedro Garcia Lorente"
      ], 
      "id": "10155156742626033_10155156758251033"
    }, 
    {
      "keyPhrases": [
        "Pablo Ruiz"
      ], 
      "id": "10155156742626033_10155156758271033"
    }, 
    {
      "keyPhrases": [
        "chico Iván Fita Martínez", 
        "Italia"
      ], 
      "id": "10155156742626033_10155156758311033"
    }, 
    {
      "keyPhrases": [
        "Javier Viillanueva Pichardo"
      ], 
      "id": "10155156742626033_10155156758376033"
    }, 
    {
      "keyPhrases": [
        "tierras italianas", 
        "Barrera"
      ], 
      "id": "10155156742626033_10155156758536033"
    }, 
    {
      "keyPhrases": [
        "Italia", 
        "Jose Maria Ara"
      ], 
      "id": "10155156742626033_10155156758636033"
    }, 
    {
      "keyPhrases": [
        "italianas Benedetta", 
        "Bartolomeo Naomi Damiani Giorgia Stoppaccioli", 
        "poder", 
        "Noemi Moreno"
      ], 
      "id": "10155156742626033_10155156758686033"
    }, 
    {
      "keyPhrases": [
        "Diaz Cabello"
      ], 
      "id": "10155156742626033_10155156758731033"
    }, 
    {
      "keyPhrases": [
        "Yaime GR"
      ], 
      "id": "10155156742626033_10155156758836033"
    }, 
    {
      "keyPhrases": [
        "Marina Collado  Firenze"
      ], 
      "id": "10155156742626033_10155156759026033"
    }, 
    {
      "keyPhrases": [
        "Laura López Fortes"
      ], 
      "id": "10155156742626033_10155156759231033"
    }, 
    {
      "keyPhrases": [
        "Carmen Lopez", 
        "Mamii", 
        "Italia"
      ], 
      "id": "10155156742626033_10155156759451033"
    }, 
    {
      "keyPhrases": [
        "Bella aaaaa Italiaaaaa", 
        "Leonor Garcia", 
        "estaria"
      ], 
      "id": "10155156742626033_10155156759486033"
    }, 
    {
      "keyPhrases": [
        "Monica Martinez Bermudez a Venecia"
      ], 
      "id": "10155156742626033_10155156759526033"
    }, 
    {
      "keyPhrases": [
        "Mar Rodriguez", 
        "vencida"
      ], 
      "id": "10155156742626033_10155156759546033"
    }, 
    {
      "keyPhrases": [
        "Meri Macías Guardiet"
      ], 
      "id": "10155156742626033_10155156759661033"
    }, 
    {
      "keyPhrases": [
        "Querubina AD"
      ], 
      "id": "10155156742626033_10155156759686033"
    }, 
    {
      "keyPhrases": [], 
      "id": "10155156742626033_10155156759701033"
    }, 
    {
      "keyPhrases": [
        "bellisima Italia", 
        "llevaria", 
        "marido Jorge Real"
      ], 
      "id": "10155156742626033_10155156759746033"
    }, 
    {
      "keyPhrases": [
        "Zaida"
      ], 
      "id": "10155156742626033_10155156759781033"
    }, 
    {
      "keyPhrases": [
        "Juanfra Guisado"
      ], 
      "id": "10155156742626033_10155156759836033"
    }, 
    {
      "keyPhrases": [
        "Krist Ynamirä", 
        "Roma"
      ], 
      "id": "10155156742626033_10155156760116033"
    }, 
    {
      "keyPhrases": [
        "Abel Gil Pensado"
      ], 
      "id": "10155156742626033_10155156760286033"
    }, 
    {
      "keyPhrases": [
        "día", 
        "Katie Woods"
      ], 
      "id": "10155156742626033_10155156760526033"
    }, 
    {
      "keyPhrases": [
        "papi", 
        "Baljeet Singh Gill", 
        "hijo"
      ], 
      "id": "10155156742626033_10155156760921033"
    }, 
    {
      "keyPhrases": [
        "Raul Marcos Ruiz", 
        "Italia"
      ], 
      "id": "10155156742626033_10155156761126033"
    }, 
    {
      "keyPhrases": [
        "Marta Alonso Hernandez", 
        "pizza napolitana"
      ], 
      "id": "10155156742626033_10155156761131033"
    }, 
    {
      "keyPhrases": [
        "Eva Gómez García", 
        "Ráfaga Erre De RoMán"
      ], 
      "id": "10155156742626033_10155156761571033"
    }, 
    {
      "keyPhrases": [
        "Roberto Pozo Calle"
      ], 
      "id": "10155156742626033_10155156761601033"
    }, 
    {
      "keyPhrases": [
        "Maria Pepita Pulgarcita viajeeeeeeeeeeeee"
      ], 
      "id": "10155156742626033_10155156761661033"
    }, 
    {
      "keyPhrases": [
        "Gregorio"
      ], 
      "id": "10155156742626033_10155156761716033"
    }, 
    {
      "keyPhrases": [
        "hermana Olga Pérez Romero", 
        "viajecito"
      ], 
      "id": "10155156742626033_10155156761736033"
    }, 
    {
      "keyPhrases": [
        "Omar Morón"
      ], 
      "id": "10155156742626033_10155156761781033"
    }, 
    {
      "keyPhrases": [
        "Roma", 
        "hermana Ana Trillo"
      ], 
      "id": "10155156742626033_10155156761906033"
    }, 
    {
      "keyPhrases": [
        "Lorena Jiménez"
      ], 
      "id": "10155156742626033_10155156762376033"
    }, 
    {
      "keyPhrases": [
        "Amanda Martinez Gracia"
      ], 
      "id": "10155156742626033_10155156762381033"
    }, 
    {
      "keyPhrases": [
        "Eloi Esmet"
      ], 
      "id": "10155156742626033_10155156762451033"
    }, 
    {
      "keyPhrases": [
        "destino", 
        "Olalla Montes", 
        "compañia", 
        "falta", 
        "momentos"
      ], 
      "id": "10155156742626033_10155156762486033"
    }, 
    {
      "keyPhrases": [
        "Monica PM alla vamossss"
      ], 
      "id": "10155156742626033_10155156762551033"
    }, 
    {
      "keyPhrases": [
        "bella Italia", 
        "Alberto"
      ], 
      "id": "10155156742626033_10155156762601033"
    }, 
    {
      "keyPhrases": [
        "Manuel Vallejo Pinto a Florencia"
      ], 
      "id": "10155156742626033_10155156762661033"
    }, 
    {
      "keyPhrases": [
        "Miguel Rodríguez", 
        "iria"
      ], 
      "id": "10155156742626033_10155156762846033"
    }, 
    {
      "keyPhrases": [
        "marido Javier Cobos"
      ], 
      "id": "10155156742626033_10155156762886033"
    }, 
    {
      "keyPhrases": [
        "Edu Mendez Alvarez", 
        "buena pizza"
      ], 
      "id": "10155156742626033_10155156762986033"
    }, 
    {
      "keyPhrases": [
        "Maria Gonzalez"
      ], 
      "id": "10155156742626033_10155156763266033"
    }, 
    {
      "keyPhrases": [
        "Javi Sánchez"
      ], 
      "id": "10155156742626033_10155156763316033"
    }
  ], 
  "errors": [
    {
      "message": "Supplied language is not supported. Pass in one of: de,en,es,fi,fr,it,ja,nl,pl,pt-BR,pt-PT,sv. See https://docs.microsoft.com/en-us/azure/cognitive-services/text-analytics/overview for the complete list of support languages.", 
      "id": "10155157453696033_10155159660406033"
    }, 
    {
      "message": "Supplied language is not supported. Pass in one of: de,en,es,fi,fr,it,ja,nl,pl,pt-BR,pt-PT,sv. See https://docs.microsoft.com/en-us/azure/cognitive-services/text-analytics/overview for the complete list of support languages.", 
      "id": "10155157453696033_10155160695121033"
    }, 
    {
      "message": "Supplied language is not supported. Pass in one of: de,en,es,fi,fr,it,ja,nl,pl,pt-BR,pt-PT,sv. See https://docs.microsoft.com/en-us/azure/cognitive-services/text-analytics/overview for the complete list of support languages.", 
      "id": "10155156742626033_10155156746901033"
    }, 
    {
      "message": "Supplied language is not supported. Pass in one of: de,en,es,fi,fr,it,ja,nl,pl,pt-BR,pt-PT,sv. See https://docs.microsoft.com/en-us/azure/cognitive-services/text-analytics/overview for the complete list of support languages.", 
      "id": "10155156742626033_10155156747601033"
    }, 
    {
      "message": "Supplied language is not supported. Pass in one of: de,en,es,fi,fr,it,ja,nl,pl,pt-BR,pt-PT,sv. See https://docs.microsoft.com/en-us/azure/cognitive-services/text-analytics/overview for the complete list of support languages.", 
      "id": "10155156742626033_10155156747916033"
    }, 
    {
      "message": "Supplied language is not supported. Pass in one of: de,en,es,fi,fr,it,ja,nl,pl,pt-BR,pt-PT,sv. See https://docs.microsoft.com/en-us/azure/cognitive-services/text-analytics/overview for the complete list of support languages.", 
      "id": "10155156742626033_10155156750431033"
    }, 
    {
      "message": "Supplied language is not supported. Pass in one of: de,en,es,fi,fr,it,ja,nl,pl,pt-BR,pt-PT,sv. See https://docs.microsoft.com/en-us/azure/cognitive-services/text-analytics/overview for the complete list of support languages.", 
      "id": "10155156742626033_10155156751646033"
    }, 
    {
      "message": "Supplied language is not supported. Pass in one of: de,en,es,fi,fr,it,ja,nl,pl,pt-BR,pt-PT,sv. See https://docs.microsoft.com/en-us/azure/cognitive-services/text-analytics/overview for the complete list of support languages.", 
      "id": "10155156742626033_10155156751906033"
    }, 
    {
      "message": "Supplied language is not supported. Pass in one of: de,en,es,fi,fr,it,ja,nl,pl,pt-BR,pt-PT,sv. See https://docs.microsoft.com/en-us/azure/cognitive-services/text-analytics/overview for the complete list of support languages.", 
      "id": "10155156742626033_10155156754691033"
    }, 
    {
      "message": "Supplied language is not supported. Pass in one of: de,en,es,fi,fr,it,ja,nl,pl,pt-BR,pt-PT,sv. See https://docs.microsoft.com/en-us/azure/cognitive-services/text-analytics/overview for the complete list of support languages.", 
      "id": "10155156742626033_10155156755431033"
    }, 
    {
      "message": "Supplied language is not supported. Pass in one of: de,en,es,fi,fr,it,ja,nl,pl,pt-BR,pt-PT,sv. See https://docs.microsoft.com/en-us/azure/cognitive-services/text-analytics/overview for the complete list of support languages.", 
      "id": "10155156742626033_10155156757366033"
    }, 
    {
      "message": "Supplied language is not supported. Pass in one of: de,en,es,fi,fr,it,ja,nl,pl,pt-BR,pt-PT,sv. See https://docs.microsoft.com/en-us/azure/cognitive-services/text-analytics/overview for the complete list of support languages.", 
      "id": "10155156742626033_10155156758481033"
    }, 
    {
      "message": "Supplied language is not supported. Pass in one of: de,en,es,fi,fr,it,ja,nl,pl,pt-BR,pt-PT,sv. See https://docs.microsoft.com/en-us/azure/cognitive-services/text-analytics/overview for the complete list of support languages.", 
      "id": "10155156742626033_10155156759251033"
    }, 
    {
      "message": "Supplied language is not supported. Pass in one of: de,en,es,fi,fr,it,ja,nl,pl,pt-BR,pt-PT,sv. See https://docs.microsoft.com/en-us/azure/cognitive-services/text-analytics/overview for the complete list of support languages.", 
      "id": "10155156742626033_10155156759371033"
    }, 
    {
      "message": "Supplied language is not supported. Pass in one of: de,en,es,fi,fr,it,ja,nl,pl,pt-BR,pt-PT,sv. See https://docs.microsoft.com/en-us/azure/cognitive-services/text-analytics/overview for the complete list of support languages.", 
      "id": "10155156742626033_10155156761461033"
    }, 
    {
      "message": "Supplied language is not supported. Pass in one of: de,en,es,fi,fr,it,ja,nl,pl,pt-BR,pt-PT,sv. See https://docs.microsoft.com/en-us/azure/cognitive-services/text-analytics/overview for the complete list of support languages.", 
      "id": "10155156742626033_10155156761501033"
    }, 
    {
      "message": "Supplied language is not supported. Pass in one of: de,en,es,fi,fr,it,ja,nl,pl,pt-BR,pt-PT,sv. See https://docs.microsoft.com/en-us/azure/cognitive-services/text-analytics/overview for the complete list of support languages.", 
      "id": "10155156742626033_10155156761696033"
    }, 
    {
      "message": "Supplied language is not supported. Pass in one of: de,en,es,fi,fr,it,ja,nl,pl,pt-BR,pt-PT,sv. See https://docs.microsoft.com/en-us/azure/cognitive-services/text-analytics/overview for the complete list of support languages.", 
      "id": "10155156742626033_10155156762716033"
    }, 
    {
      "message": "Supplied language is not supported. Pass in one of: de,en,es,fi,fr,it,ja,nl,pl,pt-BR,pt-PT,sv. See https://docs.microsoft.com/en-us/azure/cognitive-services/text-analytics/overview for the complete list of support languages.", 
      "id": "10155156742626033_10155156763311033"
    }
  ]
}